montecarlo/MonteCarloSimulation.py
montecarlo/__init__.py
montecarlo/__main__.py
mc_option_simulator_yale-0.0.8.dist-info/LICENSE
mc_option_simulator_yale-0.0.8.dist-info/METADATA
mc_option_simulator_yale-0.0.8.dist-info/WHEEL
mc_option_simulator_yale-0.0.8.dist-info/entry_points.txt
mc_option_simulator_yale-0.0.8.dist-info/top_level.txt
mc_option_simulator_yale-0.0.8.dist-info/RECORD
