Metadata-Version: 2.1
Name: mc-option-simulator-yale
Version: 0.0.8
Summary: CLI for Geometric Brownian Motion and Black Scholes Math for Monte Carlo Simulation
Home-page: https://github.com/yalehacks/MonteMath
Author: Chase Coogan
Author-email: chasecoogan12@gmail.com
License: MIT
Project-URL: Bug Reports, https://github.com/yalehacks/MonteMath
Project-URL: Source, https://github.com/yalehacks/MonteMath
Classifier: Programming Language :: Python :: 3
Classifier: License :: OSI Approved :: MIT License
Classifier: Operating System :: OS Independent
Classifier: Topic :: Scientific/Engineering :: Mathematics
Classifier: Topic :: Scientific/Engineering
Requires-Python: >=3.8
License-File: LICENSE
Requires-Dist: numpy
Requires-Dist: scipy
